backshift
backshift-extracts
backshift-one
backshift-recent-backup-id
backshift-verify-file
backshift-verify-filesystem
backshift_file_mod.py
backshift_os_mod.py
base255.py
bloom_filter_mod.py
bufsock.py
cacher_mod.py
chunk_mod.py
comma_mod.py
compressed_file_mod.py
compressed_string_mod.py
constants_mod.py
count
db_mod.py
dirops_mod.py
dohdbm.py
escape_mod.py
expire_mod.py
file_count_mod.py
get_chunk.py
hardlinks_mod.py
helpers.py
main.py
metadata_mod.py
modunits.py
readline0.py
repo_mod.py
saveset_files_mod.py
saveset_summary_mod.py
setup.py
sshfs-backup
stringio.py
strip-components
touch.py
xz_mod.py
zst_mod.py
zst_zstandard.py
backshift.egg-info/PKG-INFO
backshift.egg-info/SOURCES.txt
backshift.egg-info/dependency_links.txt
backshift.egg-info/requires.txt
backshift.egg-info/top_level.txt