Metadata-Version: 2.1
Name: backshift
Version: 1.61
Summary: Filesystem to filesystem backup (deduplicated, compressed)
Home-page: http://stromberg.dnsalias.org/~strombrg/backshift/
Author: Daniel Richard Stromberg
Author-email: strombrg@gmail.com
License: GPL, MIT, UCI, Apache (all opensource)
Platform: Cross platform
Classifier: Development Status :: 5 - Production/Stable
Classifier: Intended Audience :: Developers
Classifier: Programming Language :: Python :: 3
